RinUI/__init__.py
RinUI/qmldir
RinUI/assets/fonts/FluentSystemIcons-Index.js
RinUI/assets/fonts/FluentSystemIcons-Resizable.ttf
RinUI/assets/img/default_app_icon.png
RinUI/components/Base.qml
RinUI/components/ContextMenu.qml
RinUI/components/FocusIndicator.qml
RinUI/components/Icon.qml
RinUI/components/Indicator.qml
RinUI/components/ScrollBar.qml
RinUI/components/ScrollView.qml
RinUI/components/Shadow.qml
RinUI/components/qmldir
RinUI/components/BasicInput/Button.qml
RinUI/components/BasicInput/CheckBox.qml
RinUI/components/BasicInput/ColorPicker.qml
RinUI/components/BasicInput/ComboBox.qml
RinUI/components/BasicInput/DropDownButton.qml
RinUI/components/BasicInput/DropDownColorPicker.qml
RinUI/components/BasicInput/Hyperlink.qml
RinUI/components/BasicInput/PillButton.qml
RinUI/components/BasicInput/RadioButton.qml
RinUI/components/BasicInput/RoundButton.qml
RinUI/components/BasicInput/Slider.qml
RinUI/components/BasicInput/Switch.qml
RinUI/components/BasicInput/ToggleButton.qml
RinUI/components/BasicInput/ToolButton.qml
RinUI/components/DateAndTime/Calendar.qml
RinUI/components/DateAndTime/CalendarDatePicker.qml
RinUI/components/DateAndTime/DatePicker.qml
RinUI/components/DateAndTime/PickerView.qml
RinUI/components/DateAndTime/TimePicker.qml
RinUI/components/DialogsAndFlyouts/Dialog.qml
RinUI/components/DialogsAndFlyouts/DialogButtonBox.qml
RinUI/components/DialogsAndFlyouts/Flyout.qml
RinUI/components/DialogsAndFlyouts/Popup.qml
RinUI/components/Layout/Expander.qml
RinUI/components/Layout/SettingExpander.qml
RinUI/components/Layout/SettingItem.qml
RinUI/components/ListAndCollections/Clip.qml
RinUI/components/ListAndCollections/Frame.qml
RinUI/components/ListAndCollections/ListView.qml
RinUI/components/ListAndCollections/ListViewDelegate.qml
RinUI/components/ListAndCollections/SettingCard.qml
RinUI/components/ListAndCollections/TableView.qml
RinUI/components/ListAndCollections/TableViewDelegate.qml
RinUI/components/Media/Avatar.qml
rinui-0.2.0.dist-info/METADATA
rinui-0.2.0.dist-info/WHEEL
rinui-0.2.0.dist-info/entry_points.txt
rinui-0.2.0.dist-info/licenses/LICENSE
rinui-0.2.0.dist-info/RECORD
