Metadata-Version: 2.4
Name: RinUI
Version: 0.2.0
Summary: A Fluent Design-like UI library for Qt Quick (QML) based on PySide6
Author-email: RinLit <lintu233_qwq@icloud.com>
License: MIT License
License-File: LICENSE
Classifier: Operating System :: OS Independent
Classifier: Programming Language :: Python :: 3
Requires-Python: >=3.9
Requires-Dist: darkdetect~=0.8.0
Requires-Dist: pyside6>=6.9.3
Requires-Dist: pywin32; sys_platform == 'win32'
Provides-Extra: dev
Requires-Dist: pre-commit>=4.0.0; extra == 'dev'
Requires-Dist: ruff>=0.14.0; extra == 'dev'
